psdec/__init__.cpython-310-x86_64-linux-gnu.so
psdec/mac_code.cpython-310-x86_64-linux-gnu.so
psdec/register.cpython-310-x86_64-linux-gnu.so
psdec/verifier.cpython-310-x86_64-linux-gnu.so
psdec-0.1.1.dist-info/METADATA
psdec-0.1.1.dist-info/WHEEL
psdec-0.1.1.dist-info/entry_points.txt
psdec-0.1.1.dist-info/top_level.txt
psdec-0.1.1.dist-info/RECORD
psdec-0.1.1.dist-info/licenses/LICENSE.txt
