Metadata-Version: 2.4
Name: psdec
Version: 0.1.1
Summary: A sample Python project
Author-email: iepanda <iepanda@outlook.com>
Maintainer-email: PulSpread <iepanda@outlook.com>
License-Expression: MIT
Keywords: psdec,setuptools,development
Classifier: Development Status :: 3 - Alpha
Classifier: Intended Audience :: Developers
Classifier: Topic :: Software Development :: Build Tools
Classifier: Programming Language :: Python :: 3
Classifier: Programming Language :: Python :: 3.9
Classifier: Programming Language :: Python :: 3.10
Classifier: Programming Language :: Python :: 3.11
Classifier: Programming Language :: Python :: 3.12
Classifier: Programming Language :: Python :: 3.13
Classifier: Programming Language :: Python :: 3 :: Only
Requires-Python: >=3.9
License-File: LICENSE.txt
Requires-Dist: getmac
Requires-Dist: py-cpuinfo
Requires-Dist: pycryptodome
Requires-Dist: loguru
Requires-Dist: psutil
Requires-Dist: pyudev
Provides-Extra: dev
Requires-Dist: check-manifest; extra == "dev"
Provides-Extra: test
Requires-Dist: pytest; extra == "test"
Dynamic: license-file
